[
  {
    "build": "tracked-dist",
    "publicDemo": false,
    "family": "luna-core",
    "schema": "luna_pinyin",
    "samples": 1,
    "initialized": 1,
    "medianReadyToInputMs": 1003,
    "p95ReadyToInputMs": 1003,
    "medianInputToCandidateMs": 79,
    "medianCommitMs": 17,
    "medianWasmReadyBytes": 67108864,
    "medianWasmPeakBytes": 67108864,
    "maxWasmPeakBytes": 67108864,
    "medianSteadyStateBytes": 67108864,
    "medianLoadedSharedAssetBytes": 27380264,
    "medianRequestedFamilyBytes": 27380264,
    "medianUniqueEncodedResourceBytes": 30870592,
    "medianJSHeapUsedBytes": 4722164,
    "medianStorageUsageBytes": 15881,
    "loadedAssetCount": 23,
    "loadedAssets": [
      "default.custom.yaml",
      "pinyin.yaml",
      "key_bindings.yaml",
      "punctuation.yaml",
      "symbols.yaml",
      "essay.txt",
      "luna_pinyin.schema.yaml",
      "luna_pinyin.dict.yaml",
      "luna_pinyin.table.bin",
      "luna_pinyin.reverse.bin",
      "luna_pinyin.prism.bin",
      "stroke.schema.yaml",
      "stroke.dict.yaml",
      "stroke.table.bin",
      "stroke.reverse.bin",
      "stroke.prism.bin",
      "opencc/t2hk.json",
      "opencc/t2s.json",
      "opencc/t2tw.json",
      "opencc/HKVariants.ocd2",
      "opencc/TSCharacters.ocd2",
      "opencc/TSPhrases.ocd2",
      "opencc/TWVariants.ocd2"
    ],
    "consoleErrors": []
  },
  {
    "build": "public-demo-dist",
    "publicDemo": true,
    "family": "luna-core",
    "schema": "luna_pinyin",
    "samples": 1,
    "initialized": 1,
    "medianReadyToInputMs": 989,
    "p95ReadyToInputMs": 989,
    "medianInputToCandidateMs": 79,
    "medianCommitMs": 122,
    "medianWasmReadyBytes": 67108864,
    "medianWasmPeakBytes": 67108864,
    "maxWasmPeakBytes": 67108864,
    "medianSteadyStateBytes": 67108864,
    "medianLoadedSharedAssetBytes": 27380264,
    "medianRequestedFamilyBytes": 27380264,
    "medianUniqueEncodedResourceBytes": 30882773,
    "medianJSHeapUsedBytes": 4727244,
    "medianStorageUsageBytes": 27427857,
    "loadedAssetCount": 23,
    "loadedAssets": [
      "default.custom.yaml",
      "pinyin.yaml",
      "key_bindings.yaml",
      "punctuation.yaml",
      "symbols.yaml",
      "essay.txt",
      "luna_pinyin.schema.yaml",
      "luna_pinyin.dict.yaml",
      "luna_pinyin.table.bin",
      "luna_pinyin.reverse.bin",
      "luna_pinyin.prism.bin",
      "stroke.schema.yaml",
      "stroke.dict.yaml",
      "stroke.table.bin",
      "stroke.reverse.bin",
      "stroke.prism.bin",
      "opencc/t2hk.json",
      "opencc/t2s.json",
      "opencc/t2tw.json",
      "opencc/HKVariants.ocd2",
      "opencc/TSCharacters.ocd2",
      "opencc/TSPhrases.ocd2",
      "opencc/TWVariants.ocd2"
    ],
    "consoleErrors": []
  },
  {
    "build": "tracked-dist",
    "publicDemo": false,
    "family": "jyutping-core",
    "schema": "jyut6ping3_mobile",
    "samples": 1,
    "initialized": 1,
    "medianReadyToInputMs": 1003,
    "p95ReadyToInputMs": 1003,
    "medianInputToCandidateMs": 69,
    "medianCommitMs": 121,
    "medianWasmReadyBytes": 167772160,
    "medianWasmPeakBytes": 167772160,
    "maxWasmPeakBytes": 167772160,
    "medianSteadyStateBytes": 167772160,
    "medianLoadedSharedAssetBytes": 38165332,
    "medianRequestedFamilyBytes": 38165332,
    "medianUniqueEncodedResourceBytes": 45140189,
    "medianJSHeapUsedBytes": 4905400,
    "medianStorageUsageBytes": 23926,
    "loadedAssetCount": 10,
    "loadedAssets": [
      "default.custom.yaml",
      "common.yaml",
      "common.custom.yaml",
      "include.yaml",
      "template.yaml",
      "jyut6ping3.schema.yaml",
      "jyut6ping3_mobile.schema.yaml",
      "jyut6ping3.table.bin",
      "jyut6ping3.reverse.bin",
      "jyut6ping3_mobile.prism.bin"
    ],
    "consoleErrors": []
  },
  {
    "build": "public-demo-dist",
    "publicDemo": true,
    "family": "jyutping-core",
    "schema": "jyut6ping3_mobile",
    "samples": 1,
    "initialized": 1,
    "medianReadyToInputMs": 1096,
    "p95ReadyToInputMs": 1096,
    "medianInputToCandidateMs": 80,
    "medianCommitMs": 110,
    "medianWasmReadyBytes": 167772160,
    "medianWasmPeakBytes": 167772160,
    "maxWasmPeakBytes": 167772160,
    "medianSteadyStateBytes": 167772160,
    "medianLoadedSharedAssetBytes": 38165332,
    "medianRequestedFamilyBytes": 38165332,
    "medianUniqueEncodedResourceBytes": 45152370,
    "medianJSHeapUsedBytes": 4916176,
    "medianStorageUsageBytes": 41695614,
    "loadedAssetCount": 10,
    "loadedAssets": [
      "default.custom.yaml",
      "common.yaml",
      "common.custom.yaml",
      "include.yaml",
      "template.yaml",
      "jyut6ping3.schema.yaml",
      "jyut6ping3_mobile.schema.yaml",
      "jyut6ping3.table.bin",
      "jyut6ping3.reverse.bin",
      "jyut6ping3_mobile.prism.bin"
    ],
    "consoleErrors": []
  },
  {
    "build": "tracked-dist",
    "publicDemo": false,
    "family": "jyutping-scolar",
    "schema": "jyut6ping3_mobile",
    "samples": 1,
    "initialized": 1,
    "medianReadyToInputMs": 1123,
    "p95ReadyToInputMs": 1123,
    "medianInputToCandidateMs": 104,
    "medianCommitMs": 107,
    "medianWasmReadyBytes": 167772160,
    "medianWasmPeakBytes": 167772160,
    "maxWasmPeakBytes": 167772160,
    "medianSteadyStateBytes": 167772160,
    "medianLoadedSharedAssetBytes": 57772609,
    "medianRequestedFamilyBytes": 57772609,
    "medianUniqueEncodedResourceBytes": 64747466,
    "medianJSHeapUsedBytes": 4952448,
    "medianStorageUsageBytes": 23930,
    "loadedAssetCount": 15,
    "loadedAssets": [
      "default.custom.yaml",
      "common.yaml",
      "common.custom.yaml",
      "include.yaml",
      "template.yaml",
      "jyut6ping3.schema.yaml",
      "jyut6ping3_mobile.schema.yaml",
      "jyut6ping3.table.bin",
      "jyut6ping3.reverse.bin",
      "jyut6ping3_mobile.prism.bin",
      "jyut6ping3_scolar.schema.yaml",
      "jyut6ping3_scolar.dict.yaml",
      "jyut6ping3_scolar.table.bin",
      "jyut6ping3_scolar.reverse.bin",
      "jyut6ping3_scolar.prism.bin"
    ],
    "consoleErrors": []
  },
  {
    "build": "public-demo-dist",
    "publicDemo": true,
    "family": "jyutping-scolar",
    "schema": "jyut6ping3_mobile",
    "samples": 1,
    "initialized": 1,
    "medianReadyToInputMs": 1289,
    "p95ReadyToInputMs": 1289,
    "medianInputToCandidateMs": 89,
    "medianCommitMs": 117,
    "medianWasmReadyBytes": 167772160,
    "medianWasmPeakBytes": 167772160,
    "maxWasmPeakBytes": 167772160,
    "medianSteadyStateBytes": 167772160,
    "medianLoadedSharedAssetBytes": 57772609,
    "medianRequestedFamilyBytes": 57772609,
    "medianUniqueEncodedResourceBytes": 64759647,
    "medianJSHeapUsedBytes": 4952056,
    "medianStorageUsageBytes": 61308802,
    "loadedAssetCount": 15,
    "loadedAssets": [
      "default.custom.yaml",
      "common.yaml",
      "common.custom.yaml",
      "include.yaml",
      "template.yaml",
      "jyut6ping3.schema.yaml",
      "jyut6ping3_mobile.schema.yaml",
      "jyut6ping3.table.bin",
      "jyut6ping3.reverse.bin",
      "jyut6ping3_mobile.prism.bin",
      "jyut6ping3_scolar.schema.yaml",
      "jyut6ping3_scolar.dict.yaml",
      "jyut6ping3_scolar.table.bin",
      "jyut6ping3_scolar.reverse.bin",
      "jyut6ping3_scolar.prism.bin"
    ],
    "consoleErrors": []
  },
  {
    "build": "tracked-dist",
    "publicDemo": false,
    "family": "reverse-lookup",
    "schema": "jyut6ping3_mobile",
    "samples": 1,
    "initialized": 1,
    "medianReadyToInputMs": 1214,
    "p95ReadyToInputMs": 1214,
    "medianInputToCandidateMs": 93,
    "medianCommitMs": 106,
    "medianWasmReadyBytes": 167772160,
    "medianWasmPeakBytes": 167772160,
    "maxWasmPeakBytes": 167772160,
    "medianSteadyStateBytes": 167772160,
    "medianLoadedSharedAssetBytes": 41630571,
    "medianRequestedFamilyBytes": 53343254,
    "medianUniqueEncodedResourceBytes": 48605428,
    "medianJSHeapUsedBytes": 4900300,
    "medianStorageUsageBytes": 23928,
    "loadedAssetCount": 18,
    "loadedAssets": [
      "default.custom.yaml",
      "common.yaml",
      "common.custom.yaml",
      "include.yaml",
      "template.yaml",
      "jyut6ping3.schema.yaml",
      "jyut6ping3_mobile.schema.yaml",
      "jyut6ping3.table.bin",
      "jyut6ping3.reverse.bin",
      "jyut6ping3_mobile.prism.bin",
      "loengfan.schema.yaml",
      "loengfan.dict.yaml",
      "cangjie3.schema.yaml",
      "cangjie3.dict.yaml",
      "cangjie5.schema.yaml",
      "cangjie5.dict.yaml",
      "luna_pinyin.dict.yaml",
      "luna_pinyin_yune_reverse.dict.yaml"
    ],
    "consoleErrors": []
  },
  {
    "build": "public-demo-dist",
    "publicDemo": true,
    "family": "reverse-lookup",
    "schema": "jyut6ping3_mobile",
    "samples": 1,
    "initialized": 1,
    "medianReadyToInputMs": 3432,
    "p95ReadyToInputMs": 3432,
    "medianInputToCandidateMs": 71,
    "medianCommitMs": 106,
    "medianWasmReadyBytes": 167772160,
    "medianWasmPeakBytes": 167772160,
    "maxWasmPeakBytes": 167772160,
    "medianSteadyStateBytes": 167772160,
    "medianLoadedSharedAssetBytes": 41630571,
    "medianRequestedFamilyBytes": 53343254,
    "medianUniqueEncodedResourceBytes": 48617609,
    "medianJSHeapUsedBytes": 4929040,
    "medianStorageUsageBytes": 45169536,
    "loadedAssetCount": 18,
    "loadedAssets": [
      "default.custom.yaml",
      "common.yaml",
      "common.custom.yaml",
      "include.yaml",
      "template.yaml",
      "jyut6ping3.schema.yaml",
      "jyut6ping3_mobile.schema.yaml",
      "jyut6ping3.table.bin",
      "jyut6ping3.reverse.bin",
      "jyut6ping3_mobile.prism.bin",
      "loengfan.schema.yaml",
      "loengfan.dict.yaml",
      "cangjie3.schema.yaml",
      "cangjie3.dict.yaml",
      "cangjie5.schema.yaml",
      "cangjie5.dict.yaml",
      "luna_pinyin.dict.yaml",
      "luna_pinyin_yune_reverse.dict.yaml"
    ],
    "consoleErrors": []
  },
  {
    "build": "tracked-dist",
    "publicDemo": false,
    "family": "opencc",
    "schema": "jyut6ping3_mobile",
    "samples": 1,
    "initialized": 1,
    "medianReadyToInputMs": 1209,
    "p95ReadyToInputMs": 1209,
    "medianInputToCandidateMs": 69,
    "medianCommitMs": 111,
    "medianWasmReadyBytes": 167772160,
    "medianWasmPeakBytes": 167772160,
    "maxWasmPeakBytes": 167772160,
    "medianSteadyStateBytes": 167772160,
    "medianLoadedSharedAssetBytes": 38235649,
    "medianRequestedFamilyBytes": 38235649,
    "medianUniqueEncodedResourceBytes": 45210506,
    "medianJSHeapUsedBytes": 4900316,
    "medianStorageUsageBytes": 23912,
    "loadedAssetCount": 19,
    "loadedAssets": [
      "default.custom.yaml",
      "common.yaml",
      "common.custom.yaml",
      "include.yaml",
      "template.yaml",
      "jyut6ping3.schema.yaml",
      "jyut6ping3_mobile.schema.yaml",
      "jyut6ping3.table.bin",
      "jyut6ping3.reverse.bin",
      "jyut6ping3_mobile.prism.bin",
      "opencc/t2hkf.json",
      "opencc/HKVariantsFull.txt",
      "opencc/t2s.json",
      "opencc/t2tw.json",
      "opencc/hk2s.json",
      "opencc/HKVariantsRev.ocd2",
      "opencc/HKVariantsRevPhrases.ocd2",
      "opencc/TSCharacters.ocd2",
      "opencc/TSPhrases.ocd2"
    ],
    "consoleErrors": []
  },
  {
    "build": "public-demo-dist",
    "publicDemo": true,
    "family": "opencc",
    "schema": "jyut6ping3_mobile",
    "samples": 1,
    "initialized": 1,
    "medianReadyToInputMs": 1541,
    "p95ReadyToInputMs": 1541,
    "medianInputToCandidateMs": 87,
    "medianCommitMs": 108,
    "medianWasmReadyBytes": 167772160,
    "medianWasmPeakBytes": 167772160,
    "maxWasmPeakBytes": 167772160,
    "medianSteadyStateBytes": 167772160,
    "medianLoadedSharedAssetBytes": 38235649,
    "medianRequestedFamilyBytes": 38235649,
    "medianUniqueEncodedResourceBytes": 45222687,
    "medianJSHeapUsedBytes": 4931060,
    "medianStorageUsageBytes": 41775216,
    "loadedAssetCount": 19,
    "loadedAssets": [
      "default.custom.yaml",
      "common.yaml",
      "common.custom.yaml",
      "include.yaml",
      "template.yaml",
      "jyut6ping3.schema.yaml",
      "jyut6ping3_mobile.schema.yaml",
      "jyut6ping3.table.bin",
      "jyut6ping3.reverse.bin",
      "jyut6ping3_mobile.prism.bin",
      "opencc/t2hkf.json",
      "opencc/HKVariantsFull.txt",
      "opencc/t2s.json",
      "opencc/t2tw.json",
      "opencc/hk2s.json",
      "opencc/HKVariantsRev.ocd2",
      "opencc/HKVariantsRevPhrases.ocd2",
      "opencc/TSCharacters.ocd2",
      "opencc/TSPhrases.ocd2"
    ],
    "consoleErrors": []
  },
  {
    "build": "tracked-dist",
    "publicDemo": false,
    "family": "extras",
    "schema": "jyut6ping3_mobile",
    "samples": 1,
    "initialized": 1,
    "medianReadyToInputMs": 5232,
    "p95ReadyToInputMs": 5232,
    "medianInputToCandidateMs": 79,
    "medianCommitMs": 109,
    "medianWasmReadyBytes": 936509440,
    "medianWasmPeakBytes": 936509440,
    "maxWasmPeakBytes": 936509440,
    "medianSteadyStateBytes": 936509440,
    "medianLoadedSharedAssetBytes": 0,
    "medianRequestedFamilyBytes": 0,
    "medianUniqueEncodedResourceBytes": 6976624,
    "medianJSHeapUsedBytes": 4968120,
    "medianStorageUsageBytes": 23912,
    "loadedAssetCount": 0,
    "loadedAssets": [],
    "consoleErrors": []
  },
  {
    "build": "public-demo-dist",
    "publicDemo": true,
    "family": "extras",
    "schema": "jyut6ping3_mobile",
    "samples": 1,
    "initialized": 1,
    "medianReadyToInputMs": 5178,
    "p95ReadyToInputMs": 5178,
    "medianInputToCandidateMs": 72,
    "medianCommitMs": 117,
    "medianWasmReadyBytes": 936509440,
    "medianWasmPeakBytes": 936509440,
    "maxWasmPeakBytes": 936509440,
    "medianSteadyStateBytes": 936509440,
    "medianLoadedSharedAssetBytes": 0,
    "medianRequestedFamilyBytes": 0,
    "medianUniqueEncodedResourceBytes": 6988805,
    "medianJSHeapUsedBytes": 5010672,
    "medianStorageUsageBytes": 3522416,
    "loadedAssetCount": 0,
    "loadedAssets": [],
    "consoleErrors": []
  },
  {
    "build": "tracked-dist",
    "publicDemo": false,
    "family": "full-jyutping",
    "schema": "jyut6ping3_mobile",
    "samples": 1,
    "initialized": 1,
    "medianReadyToInputMs": 1205,
    "p95ReadyToInputMs": 1205,
    "medianInputToCandidateMs": 87,
    "medianCommitMs": 120,
    "medianWasmReadyBytes": 167772160,
    "medianWasmPeakBytes": 167772160,
    "maxWasmPeakBytes": 167772160,
    "medianSteadyStateBytes": 167772160,
    "medianLoadedSharedAssetBytes": 68725648,
    "medianRequestedFamilyBytes": 67834271,
    "medianUniqueEncodedResourceBytes": 75700505,
    "medianJSHeapUsedBytes": 4989820,
    "medianStorageUsageBytes": 23926,
    "loadedAssetCount": 35,
    "loadedAssets": [
      "default.custom.yaml",
      "common.yaml",
      "common.custom.yaml",
      "include.yaml",
      "template.yaml",
      "jyut6ping3.schema.yaml",
      "jyut6ping3_mobile.schema.yaml",
      "jyut6ping3_scolar.schema.yaml",
      "jyut6ping3_scolar.dict.yaml",
      "loengfan.schema.yaml",
      "loengfan.dict.yaml",
      "cangjie3.schema.yaml",
      "cangjie3.dict.yaml",
      "cangjie5.schema.yaml",
      "cangjie5.dict.yaml",
      "luna_pinyin.dict.yaml",
      "luna_pinyin_yune_reverse.dict.yaml",
      "luna_pinyin_yune_reverse.table.bin",
      "luna_pinyin_yune_reverse.reverse.bin",
      "luna_pinyin_yune_reverse.prism.bin",
      "opencc/t2hkf.json",
      "opencc/HKVariantsFull.txt",
      "opencc/t2s.json",
      "opencc/t2tw.json",
      "opencc/hk2s.json",
      "opencc/HKVariantsRev.ocd2",
      "opencc/HKVariantsRevPhrases.ocd2",
      "opencc/TSCharacters.ocd2",
      "opencc/TSPhrases.ocd2",
      "jyut6ping3.table.bin",
      "jyut6ping3.reverse.bin",
      "jyut6ping3_mobile.prism.bin",
      "jyut6ping3_scolar.table.bin",
      "jyut6ping3_scolar.reverse.bin",
      "jyut6ping3_scolar.prism.bin"
    ],
    "consoleErrors": []
  },
  {
    "build": "public-demo-dist",
    "publicDemo": true,
    "family": "full-jyutping",
    "schema": "jyut6ping3_mobile",
    "samples": 1,
    "initialized": 1,
    "medianReadyToInputMs": 1306,
    "p95ReadyToInputMs": 1306,
    "medianInputToCandidateMs": 100,
    "medianCommitMs": 110,
    "medianWasmReadyBytes": 167772160,
    "medianWasmPeakBytes": 167772160,
    "maxWasmPeakBytes": 167772160,
    "medianSteadyStateBytes": 167772160,
    "medianLoadedSharedAssetBytes": 68725648,
    "medianRequestedFamilyBytes": 67834271,
    "medianUniqueEncodedResourceBytes": 75712686,
    "medianJSHeapUsedBytes": 4951916,
    "medianStorageUsageBytes": 72283262,
    "loadedAssetCount": 35,
    "loadedAssets": [
      "default.custom.yaml",
      "common.yaml",
      "common.custom.yaml",
      "include.yaml",
      "template.yaml",
      "jyut6ping3.schema.yaml",
      "jyut6ping3_mobile.schema.yaml",
      "jyut6ping3_scolar.schema.yaml",
      "jyut6ping3_scolar.dict.yaml",
      "loengfan.schema.yaml",
      "loengfan.dict.yaml",
      "cangjie3.schema.yaml",
      "cangjie3.dict.yaml",
      "cangjie5.schema.yaml",
      "cangjie5.dict.yaml",
      "luna_pinyin.dict.yaml",
      "luna_pinyin_yune_reverse.dict.yaml",
      "luna_pinyin_yune_reverse.table.bin",
      "luna_pinyin_yune_reverse.reverse.bin",
      "luna_pinyin_yune_reverse.prism.bin",
      "opencc/t2hkf.json",
      "opencc/HKVariantsFull.txt",
      "opencc/t2s.json",
      "opencc/t2tw.json",
      "opencc/hk2s.json",
      "opencc/HKVariantsRev.ocd2",
      "opencc/HKVariantsRevPhrases.ocd2",
      "opencc/TSCharacters.ocd2",
      "opencc/TSPhrases.ocd2",
      "jyut6ping3.table.bin",
      "jyut6ping3.reverse.bin",
      "jyut6ping3_mobile.prism.bin",
      "jyut6ping3_scolar.table.bin",
      "jyut6ping3_scolar.reverse.bin",
      "jyut6ping3_scolar.prism.bin"
    ],
    "consoleErrors": []
  }
]
